{
  "main": {
    "id": "2f1e3df77eb4788d",
    "type": "split",
    "children": [
      {
        "id": "6d62bb15a9e41660",
        "type": "tabs",
        "children": [
          {
            "id": "9d726fd4a0bf8218",
            "type": "leaf",
            "state": {
              "type": "empty",
              "state": {},
              "icon": "lucide-file",
              "title": "New tab"
            }
          }
        ]
      }
    ],
    "direction": "vertical"
  },
  "left": {
    "id": "be4810fbdc828c0c",
    "type": "split",
    "children": [
      {
        "id": "ff7fa9087b355764",
        "type": "tabs",
        "children": [
          {
            "id": "39949ea729c6fcb7",
            "type": "leaf",
            "state": {
              "type": "file-explorer",
              "state": {
                "sortOrder": "alphabetical",
                "autoReveal": false
              },
              "icon": "lucide-folder-closed",
              "title": "Files"
            }
          },
          {
            "id": "da164d04adb59624",
            "type": "leaf",
            "state": {
              "type": "search",
              "state": {
                "query": "",
                "matchingCase": false,
                "explainSearch": false,
                "collapseAll": false,
                "extraContext": false,
                "sortOrder": "alphabetical"
              },
              "icon": "lucide-search",
              "title": "Search"
            }
          },
          {
            "id": "03a1905a4e0856ed",
            "type": "leaf",
            "state": {
              "type": "bookmarks",
              "state": {},
              "icon": "lucide-bookmark",
              "title": "Bookmarks"
            }
          }
        ]
      }
    ],
    "direction": "horizontal",
    "width": 300
  },
  "right": {
    "id": "635e4f10f7e18093",
    "type": "split",
    "children": [
      {
        "id": "68c2ab5de22c0e82",
        "type": "tabs",
        "children": [
          {
            "id": "736fe068f75de276",
            "type": "leaf",
            "state": {
              "type": "backlink",
              "state": {
                "collapseAll": false,
                "extraContext": false,
                "sortOrder": "alphabetical",
                "showSearch": false,
                "searchQuery": "",
                "backlinkCollapsed": false,
                "unlinkedCollapsed": true
              },
              "icon": "links-coming-in",
              "title": "Backlinks"
            }
          },
          {
            "id": "7d01cb377e0b846d",
            "type": "leaf",
            "state": {
              "type": "outgoing-link",
              "state": {
                "linksCollapsed": false,
                "unlinkedCollapsed": true
              },
              "icon": "links-going-out",
              "title": "Outgoing links"
            }
          },
          {
            "id": "fe360c9960569fce",
            "type": "leaf",
            "state": {
              "type": "tag",
              "state": {
                "sortOrder": "frequency",
                "useHierarchy": true,
                "showSearch": false,
                "searchQuery": ""
              },
              "icon": "lucide-tags",
              "title": "Tags"
            }
          },
          {
            "id": "9a87a3a8ebb2949d",
            "type": "leaf",
            "state": {
              "type": "outline",
              "state": {
                "followCursor": false,
                "showSearch": false,
                "searchQuery": ""
              },
              "icon": "lucide-list",
              "title": "Outline"
            }
          }
        ]
      }
    ],
    "direction": "horizontal",
    "width": 300,
    "collapsed": true
  },
  "left-ribbon": {
    "hiddenItems": {
      "switcher:Open quick switcher": false,
      "graph:Open graph view": false,
      "canvas:Create new canvas": false,
      "daily-notes:Open today's daily note": false,
      "templates:Insert template": false,
      "command-palette:Open command palette": false
    }
  },
  "active": "9d726fd4a0bf8218",
  "lastOpenFiles": []
}